{
  "fileGlobs": ["language.yml"],
  "fromVersion": "3.2.0",
  "toVersion": "3.3.0",
  "configMigrationSteps": [
    {
      "stepType": "set_string",
      "key": "command.item-groups-list",
      "value": "&6[MythicDrops] &6Item Groups: &F%itemgroups%"
    },
    {
      "stepType": "set_string",
      "key": "command.item-groups-materials-list",
      "value": "&6[MythicDrops] &6Item Group (&F%itemgroup%&6) materials: &F%materials%"
    },
    {
      "stepType": "set_string",
      "key": "command.item-group-does-not-exist",
      "value": "&6[MythicDrops] &CThat item group does not exist."
    }
  ]
}
